data/fonts/Amorino_beta.ttf
data/fonts/Barlow-Black.ttf
data/fonts/Barlow-BlackItalic.ttf
data/fonts/Barlow-Bold.ttf
data/fonts/Barlow-BoldItalic.ttf
data/fonts/Barlow-ExtraBold.ttf
data/fonts/Barlow-ExtraBoldItalic.ttf
data/fonts/Barlow-ExtraLight.ttf
data/fonts/Barlow-ExtraLightItalic.ttf
data/fonts/Barlow-Italic.ttf
data/fonts/Barlow-Light.ttf
data/fonts/Barlow-LightItalic.ttf
data/fonts/Barlow-Medium.ttf
data/fonts/Barlow-MediumItalic.ttf
data/fonts/Barlow-Regular.ttf
data/fonts/Barlow-SemiBold.ttf
data/fonts/Barlow-SemiBoldItalic.ttf
data/fonts/Barlow-Thin.ttf
data/fonts/Barlow-ThinItalic.ttf
data/fonts/BebasNeue-Bold.ttf
data/fonts/BebasNeue-Book.ttf
data/fonts/BebasNeue-Light.ttf
data/fonts/BebasNeue-Regular.ttf
data/fonts/BebasNeue-Thin.ttf
data/fonts/Bedizen.ttf
data/fonts/Blacker-Display-Bold-italic-trial.ttf
data/fonts/Blacker-Display-Bold-trial.ttf
data/fonts/Blacker-Display-ExtraBold-Italic-trial.ttf
data/fonts/Blacker-Display-ExtraBold-trial.ttf
data/fonts/Blacker-Display-Heavy-Italic-trial.ttf
data/fonts/Blacker-Display-Heavy-trial.ttf
data/fonts/Blacker-Display-Light-Italic-trial.ttf
data/fonts/Blacker-Display-Light-trial.ttf
data/fonts/Blacker-Display-Medium-Italic-trial.ttf
data/fonts/Blacker-Display-Medium-trial.ttf
data/fonts/Blacker-Display-Regular-Italic-trial.ttf
data/fonts/Blacker-Display-Regular-trial.ttf
data/fonts/Blacker-Text-Bold-Italic-trial.ttf
data/fonts/Blacker-Text-Bold-trial.ttf
data/fonts/Blacker-Text-Book-Italic-trial.ttf
data/fonts/Blacker-Text-Book-trial.ttf
data/fonts/Blacker-Text-Heavy-Italic-trial.ttf
data/fonts/Blacker-Text-Heavy-trial.ttf
data/fonts/Blacker-Text-Light-Italic-trial.ttf
data/fonts/Blacker-Text-Light-trial.ttf
data/fonts/Blacker-Text-Medium-Italic-trial.ttf
data/fonts/Blacker-Text-Medium-trial.ttf
data/fonts/Blacker-Text-Regular-Italic-trial.ttf
data/fonts/Blacker-Text-Regular-trial.ttf
data/fonts/Calibri Bold Italic.ttf
data/fonts/Calibri Bold.ttf
data/fonts/Calibri Italic.ttf
xebus_id_card_image_generator-1.4.1.dist-info/LICENSE.md
xebus_id_card_image_generator-1.4.1.dist-info/WHEEL
xebus_id_card_image_generator-1.4.1.dist-info/METADATA
xebus_id_card_image_generator-1.4.1.dist-info/RECORD
