Metadata-Version: 2.1
Name: xebus-id-card-image-generator
Version: 1.4.1
Summary: Command-Line Interface (CLI) to generate JPEG images of Xebus ID cards
Home-page: https://github.com/xebus/xebus-id-card-image-generator
License: SEE LICENSE IN <LICENSE.md>
Keywords: card,generator,identity,xebus
Author: Daniel CAUNE
Author-email: daniel.caune@gmail.com
Requires-Python: >=3.10,<4.0
Classifier: Development Status :: 5 - Production/Stable
Classifier: License :: Other/Proprietary License
Classifier: Operating System :: OS Independent
Classifier: Programming Language :: Python
Classifier: Programming Language :: Python :: 3
Classifier: Programming Language :: Python :: 3.10
Classifier: Programming Language :: Python :: 3.11
Classifier: Topic :: Software Development :: Libraries
Requires-Dist: Unidecode (>=1.3.8,<2.0.0)
Requires-Dist: perseus-core-library (>=1.20.3,<2.0.0)
Requires-Dist: pillow (>=10.0.1,<11.0.0)
Requires-Dist: qrcode (>=7.3.1,<8.0.0)
Requires-Dist: xebus-family-data-library (>=1.0.5,<2.0.0)
Project-URL: Repository, https://github.com/xebus/xebus-id-card-image-generator
